mitre_attack/__init__.py
mitre_attack/api/__init__.py
mitre_attack/api/client.py
mitre_attack/cli/__init__.py
mitre_attack/cli/__main__.py
mitre_attack/cli/helpers.py
mitre_attack/constants.py
mitre_attack/data/__init__.py
mitre_attack/data/types/__init__.py
mitre_attack/data/types/data_component.py
mitre_attack/data/types/data_source.py
mitre_attack/data/types/external_reference.py
mitre_attack/data/types/group.py
mitre_attack/data/types/identity.py
mitre_attack/data/types/kill_chain_phase.py
mitre_attack/data/types/malware.py
mitre_attack/data/types/marking_definition.py
mitre_attack/data/types/matrix.py
mitre_attack/data/types/mitigation.py
mitre_attack/data/types/object.py
mitre_attack/data/types/relationship.py
mitre_attack/data/types/software.py
mitre_attack/data/types/tactic.py
mitre_attack/data/types/technique.py
mitre_attack/data/types/tool.py
mitre_attack/files.py
mitre_attack/git.py
mitre_attack/logging.py
mitre_attack/pattern_matching.py
mitre_attack/serialization.py
mitre_attack/stix2.py
mitre_attack/types.py
mitre_attack-1.0.1.dist-info/entry_points.txt
mitre_attack-1.0.1.dist-info/LICENSE
mitre_attack-1.0.1.dist-info/WHEEL
mitre_attack-1.0.1.dist-info/METADATA
mitre_attack-1.0.1.dist-info/RECORD
