Metadata-Version: 2.1
Name: mitre-attack
Version: 1.0.1
Summary: 
Author: Tyler Fisher
Author-email: tylerfisher@tylerfisher.ca
Requires-Python: >=3.8,<4.0
Classifier: Programming Language :: Python :: 3
Classifier: Programming Language :: Python :: 3.10
Classifier: Programming Language :: Python :: 3.8
Classifier: Programming Language :: Python :: 3.9
Requires-Dist: GitPython (>=3.1.28,<4.0.0)
Requires-Dist: click (>=8.1.3,<9.0.0)
Requires-Dist: coverage[toml] (>=6.1.1,<7.0.0)
Requires-Dist: python-dateutil (>=2.8.2,<3.0.0)
Requires-Dist: setuptools (>=58.5.3,<59.0.0)
Requires-Dist: stix2 (>=3.0.1,<4.0.0)
Requires-Dist: taxii2-client (>=2.3.0,<3.0.0)
Requires-Dist: toml (>=0.10.2,<0.11.0)
